Metadata-Version: 2.1
Name: PyScons
Version: 1.0.92
Summary: An extension to Scons which enables dependency tracking on python script imports.
Home-page: http://swami.wustl.edu/
Author: S. Joshua Swamidass
Author-email: swamidass@gmail.com
License: UNKNOWN
Platform: UNKNOWN
Classifier: Development Status :: 5 - Production/Stable
Classifier: License :: OSI Approved :: MIT License
Classifier: Intended Audience :: Science/Research
Classifier: License :: Free for non-commercial use
Classifier: Natural Language :: English
Classifier: Topic :: Software Development :: Build Tools
Classifier: Programming Language :: Python
Classifier: Topic :: System :: Installation/Setup
Classifier: Intended Audience :: Developers
